nombrestolletres/__init__.py
nombresalletres-0.2.dist-info/LICENSE
nombresalletres-0.2.dist-info/METADATA
nombresalletres-0.2.dist-info/WHEEL
nombresalletres-0.2.dist-info/top_level.txt
nombresalletres-0.2.dist-info/RECORD
