Metadata-Version: 2.1
Name: nombresalletres
Version: 0.2
Summary: A python library to convert a number to letters in catalan
Home-page: https://github.com/oriolpiera/nombres-a-lletres
Author: AxiaCore, oriolpiera
Author-email: oriol.piera@somenergia.coop
License: MIT
Platform: UNKNOWN
